gwtrigfind/__init__.py
gwtrigfind/__main__.py
gwtrigfind/_version.py
gwtrigfind/cli.py
gwtrigfind/core.py
gwtrigfind/test_trigfind.py
gwtrigfind-0.8.4.dist-info/licenses/LICENSE
gwtrigfind-0.8.4.dist-info/METADATA
gwtrigfind-0.8.4.dist-info/WHEEL
gwtrigfind-0.8.4.dist-info/entry_points.txt
gwtrigfind-0.8.4.dist-info/top_level.txt
gwtrigfind-0.8.4.dist-info/RECORD
