Metadata-Version: 2.4
Name: gwtrigfind
Version: 0.8.4
Summary: Utility to find files archived by GW event trigger generators
Author-email: Duncan Macleod <duncan.macleod@ligo.org>
License: GPL-3.0-or-later
Project-URL: Bug Tracker, https://git.ligo.org/detchar/tools/gwtrigfind/-/issues
Project-URL: Documentation, https://gwtrigfind.readthedocs.io/
Project-URL: Source Code, https://git.ligo.org/detchar/tools/gwtrigfind.git
Classifier: Development Status :: 4 - Beta
Classifier: License :: OSI Approved :: GNU General Public License v3 or later (GPLv3+)
Classifier: Operating System :: OS Independent
Classifier: Programming Language :: Python
Classifier: Programming Language :: Python :: 3
Classifier: Programming Language :: Python :: 3.8
Classifier: Programming Language :: Python :: 3.9
Classifier: Programming Language :: Python :: 3.10
Classifier: Programming Language :: Python :: 3.11
Classifier: Programming Language :: Python :: 3.12
Classifier: Topic :: Scientific/Engineering
Requires-Python: >=3.8
License-File: LICENSE
Requires-Dist: gpstime
Requires-Dist: igwn-segments
Provides-Extra: test
Requires-Dist: pytest>=3.9.1; extra == "test"
Requires-Dist: pytest-cov>=2.4.0; extra == "test"
Provides-Extra: docs
Requires-Dist: numpydoc; extra == "docs"
Requires-Dist: sphinx; extra == "docs"
Requires-Dist: sphinx-automodapi; extra == "docs"
Requires-Dist: sphinx_rtd_theme; extra == "docs"
Requires-Dist: sphinx_tabs; extra == "docs"
Dynamic: license-file
